{
	"values": [
		"minecraft:fern",
		"minecraft:large_fern",
		"minecraft:allium",
		"caupona:fresh_wolfberry_leaves",
		{
			"id": "#neoforge:crops/asparagus",
			"required": false
		},
		{
			"id": "#neoforge:crops/cabbage",
			"required": false
		},
		{
			"id": "#neoforge:crops/leek",
			"required": false
		},
		{
			"id": "#neoforge:crops/kale",
			"required": false
		},
		{
			"id": "#neoforge:crops/lettuce",
			"required": false
		},
		{
			"id": "#neoforge:crops/cauliflower",
			"required": false
		},
		{
			"id": "#neoforge:crops/broccoli",
			"required": false
		},
		{
			"id": "#neoforge:crops/spinach",
			"required": false
		},
		{
			"id": "#neoforge:crops/brusselsprout",
			"required": false
		},
		{
			"id": "#neoforge:crops/artichoke",
			"required": false
		}
	]
}